nexuss/__init__.py
nexuss/__main__.py
nexuss/exceptions.py
nexuss/lateststamps.py
nexuss/nexuss.py
nexuss/nexusscontext.py
nexuss/nodeiterator.py
nexuss/py.typed
nexuss/sectioniterator.py
nexuss/structures.py
nexuss-4.13.1.dist-info/AUTHORS.md
nexuss-4.13.1.dist-info/LICENSE
nexuss-4.13.1.dist-info/METADATA
nexuss-4.13.1.dist-info/WHEEL
nexuss-4.13.1.dist-info/entry_points.txt
nexuss-4.13.1.dist-info/top_level.txt
nexuss-4.13.1.dist-info/RECORD
